TestRailAPIClient.py
TestRailListener.py
TestRailPreRunModifier.py
robotframework_testrail-2.0.1.dist-info/LICENSE
robotframework_testrail-2.0.1.dist-info/METADATA
robotframework_testrail-2.0.1.dist-info/WHEEL
robotframework_testrail-2.0.1.dist-info/top_level.txt
robotframework_testrail-2.0.1.dist-info/RECORD
