Metadata-Version: 2.1
Name: robotframework-testrail
Version: 2.0.1
Summary: Robot Framework library, listener and pre-run modifier for working with TestRail
Home-page: https://github.com/peterservice-rnd/robotframework-testrail
Author: JSC PETER-SERVICE
Author-email: drse_aist_all@billing.ru
License: Apache License 2.0
Keywords: testing testautomation robotframework testrail
Platform: UNKNOWN
Classifier: Development Status :: 5 - Production/Stable
Classifier: Intended Audience :: Developers
Classifier: Topic :: Software Development :: Testing
Classifier: License :: OSI Approved :: Apache Software License
Classifier: Programming Language :: Python :: 3.5
Classifier: Programming Language :: Python :: 3.6
Classifier: Framework :: Robot Framework :: Library
Requires-Dist: requests (>=2.20.0)
Requires-Dist: robotframework (>=3.0.3)
Requires-Dist: future (==0.16.0) ; python_version <= "2.7"
